Workbook

Sheet Instructions
A1: CrewPay Ledger
A2: Public demo guide for a workbook-first worker proof and pay-period ledger.
A4: What this workbook does | E4: What this workbook does not do
A5: Tracks workers, jobs, time entries, pay periods, proof exports, access changes, correction notes, schedules, and admin notices. | E5: It is not a full payroll system. It does not include payroll tax logic, HR compliance logic, worker accounts, enterprise permissions, backend storage, or paid APIs.
A8: Source of truth | E8: Worker proof protection
A9: The workbook is the Level 1 ledger. Apps and scripts are optional helpers and should write back to workbook records. | E9: Worker Proof is selected by one worker and one pay period. It must never become a crew-wide export.
A12: Inactive worker rule | E12: Correction notes
A13: Inactive workers lose future-use access only. Their historical time, pay periods, corrections, and proof stay visible. | E13: Corrections should be visible in Time Entries and Correction Log. No silent overwrite of proof records.
A16: Schedule/calendar note | E16: Admin notices
A17: Schedule and Google Calendar are planning/reference views only. Time Entries and Pay Periods remain proof. | E17: Admin Notices are one-way admin-to-worker or admin-to-all notices. They are not chat and not proof.
A20: Level 1 / 1.5 / 2 readiness | E20: Public demo safety note
A21: Level 1 is workbook-native. Level 1.5 adds optional Apps Script helpers. Level 2 can later move to a fuller app without changing the proof rules. | E21: All sample names, emails, jobs, notices, and records are fictional demo data. No private worker or client data is included.

Sheet Dashboard
A1: CrewPay Ledger Dashboard
A2: Workbook-first operating snapshot for worker proof, approvals, pay periods, and audit readiness.
A4: Active Workers | C4: Submitted Entries | E4: Approved Entries | G4: Rejected Entries
A5: =COUNTIF(Workers!$E$2:$E$200,"Active") | C5: =COUNTIF('Time Entries'!$P$2:$P$200,"Submitted") | E5: =COUNTIF('Time Entries'!$P$2:$P$200,"Approved")+COUNTIF('Time Entries'!$P$2:$P$200,"Finalized")+COUNTIF('Time Entries'!$P$2:$P$200,"Paid") | G5: =COUNTIF('Time Entries'!$P$2:$P$200,"Rejected")
A8: Current Pay Period | C8: Total Approved Hours | E8: Paid Proof Records | G8: Inactive Workers
A9: =IFERROR(INDEX('Pay Periods'!$A$2:$A$100,MATCH("Open",'Pay Periods'!$F$2:$F$100,0)),"Demo sample") | C9: =SUMIFS('Time Entries'!$J$2:$J$200,'Time Entries'!$P$2:$P$200,"Approved")+SUMIFS('Time Entries'!$J$2:$J$200,'Time Entries'!$P$2:$P$200,"Finalized")+SUMIFS('Time Entries'!$J$2:$J$200,'Time Entries'!$P$2:$P$200,"Paid") | E9: =COUNTIFS('Proof Exports'!$E$2:$E$100,"<>",'Proof Exports'!$D$2:$D$100,"<>") | G9: =COUNTIF(Workers!$E$2:$E$200,"Inactive")
A12: Corrections Pending | C12: Proof Privacy Rule | G12: Schedule Boundary
A13: =COUNTIF('Time Entries'!$S$2:$S$200,"<>") | C13: Worker Proof and exports are selected-worker / selected-pay-period only. | G13: Calendar is a planning mirror. It never becomes proof.
A16: Operational Status | E16: Demo Boundaries
A17: Worker access | B17: =IF(COUNTIF(Workers!$E$2:$E$200,"Inactive")>0,"Inactive archive present","All active") | E17: No worker accounts, backend database, payroll tax logic, HR compliance workflow, chat, or worker-to-worker messaging are part of this workbook demo.
A18: Approval queue | B18: =IF(COUNTIF('Time Entries'!$P$2:$P$200,"Submitted")>0,"Review submitted time","No submitted entries")
A19: Proof exports | B19: =IF(COUNTA('Proof Exports'!$A$2:$A$100)>0,"Export log active","No exports logged")
A20: Corrections | B20: =IF(COUNTA('Correction Log'!$A$2:$A$100)>0,"Correction log active","No corrections logged")

Sheet Workers
A1: Worker ID | B1: Worker Name | C1: Worker Email | D1: Role | E1: Access Status | F1: Created At | G1: Inactive At | H1: Notes | J1: Access rule
A2: W-1001 | B2: Maya Ellis | C2: maya.ellis@example.local | D2: Crew Lead | E2: Active | F2: 46174 | H2: Active worker for current entries. | J2: Active workers can receive future time entries. Inactive workers are proof-only for historical records.
A3: W-1002 | B3: Leo Grant | C3: leo.grant@example.local | D3: Installer | E3: Active | F3: 46174 | H3: Active worker with pending approval.
A4: W-1003 | B4: Priya Shah | C4: priya.shah@example.local | D4: Helper | E4: Inactive | F4: 46157 | G4: 46182 | H4: Inactive worker with historical proof records.

Sheet Jobs
A1: Job ID | B1: Job Name | C1: Client or Site | D1: Status | E1: Default Rate | F1: Calendar Event ID | G1: Notes | I1: Job rule
A2: J-2001 | B2: Oak Ridge Units | C2: Oak Ridge Apartments | D2: Active | E2: 32 | G2: Apartment unit prep and repairs. | I2: Closed jobs stay visible for proof history. Schedule and calendar references are not proof.
A3: J-2002 | B3: Bluebird Cafe Refresh | C3: Bluebird Cafe | D3: Active | E3: 30 | G3: Cafe refresh punch list.
A4: J-2003 | B4: Cedar Lane Repairs | C4: Cedar Lane Rentals | D4: Closed | E4: 24 | F4: cal-demo-cedar-001 | G4: Closed job retained for proof history.

Sheet Time Entries
A1: Entry ID | B1: Worker ID | C1: Worker Name | D1: Job ID | E1: Job Name | F1: Work Date | G1: Start Time | H1: End Time | I1: Break Minutes | J1: Hours | K1: Rate | L1: Gross Pay | M1: Reimbursement | N1: Deduction | O1: Net Pay | P1: Approval Status | Q1: Submitted At | R1: Approved At | S1: Correction Note | T1: Notes | V1: Workflow status guide
A2: T-3001 | B2: W-1001 | C2: =IFERROR(VLOOKUP(B2,Workers!$A:$H,2,FALSE),"") | D2: J-2001 | E2: =IFERROR(VLOOKUP(D2,Jobs!$A:$G,2,FALSE),"") | F2: 46175 | G2: 0.33333333 | H2: 0.6875 | I2: 30 | J2: =IF(OR(G2="",H2=""),"",MAX(0,(H2-G2)*24-(I2/60))) | K2: =IFERROR(VLOOKUP(D2,Jobs!$A:$G,5,FALSE),"") | L2: =IF(OR(J2="",K2=""),"",J2*K2) | M2: 35 | N2: 0 | O2: =IF(L2="","",L2+M2-N2) | P2: Approved | Q2: 46175.698 | R2: 46176.382 | T2: Unit prep and fixture checks. | V2: Draft = not submitted Submitted = needs admin review Approved/Paid = proof-ready Rejected/corrections stay visible
A3: T-3002 | B3: W-1002 | C3: =IFERROR(VLOOKUP(B3,Workers!$A:$H,2,FALSE),"") | D3: J-2001 | E3: =IFERROR(VLOOKUP(D3,Jobs!$A:$G,2,FALSE),"") | F3: 46175 | G3: 0.33333333 | H3: 0.625 | I3: 30 | J3: =IF(OR(G3="",H3=""),"",MAX(0,(H3-G3)*24-(I3/60))) | K3: =IFERROR(VLOOKUP(D3,Jobs!$A:$G,5,FALSE),"") | L3: =IF(OR(J3="",K3=""),"",J3*K3) | M3: 0 | N3: 0 | O3: =IF(L3="","",L3+M3-N3) | P3: Submitted | Q3: 46175.639 | T3: Drywall patch support pending approval.
A4: T-3003 | B4: W-1003 | C4: =IFERROR(VLOOKUP(B4,Workers!$A:$H,2,FALSE),"") | D4: J-2003 | E4: =IFERROR(VLOOKUP(D4,Jobs!$A:$G,2,FALSE),"") | F4: 46176 | G4: 0.375 | H4: 0.58333333 | I4: 0 | J4: =IF(OR(G4="",H4=""),"",MAX(0,(H4-G4)*24-(I4/60))) | K4: =IFERROR(VLOOKUP(D4,Jobs!$A:$G,5,FALSE),"") | L4: =IF(OR(J4="",K4=""),"",J4*K4) | M4: 0 | N4: 0 | O4: =IF(L4="","",L4+M4-N4) | P4: Approved | Q4: 46176.59 | R4: 46177.354 | T4: Historical approved work before inactive status.
A5: T-3004 | B5: W-1001 | C5: =IFERROR(VLOOKUP(B5,Workers!$A:$H,2,FALSE),"") | D5: J-2002 | E5: =IFERROR(VLOOKUP(D5,Jobs!$A:$G,2,FALSE),"") | F5: 46179 | G5: 0.3125 | H5: 0.5625 | I5: 0 | J5: =IF(OR(G5="",H5=""),"",MAX(0,(H5-G5)*24-(I5/60))) | K5: =IFERROR(VLOOKUP(D5,Jobs!$A:$G,5,FALSE),"") | L5: =IF(OR(J5="",K5=""),"",J5*K5) | M5: 0 | N5: 0 | O5: =IF(L5="","",L5+M5-N5) | P5: Paid | Q5: 46179.569 | R5: 46180.417 | S5: Paid period proof generated after final punch list. | T5: Final punch list.
A6: T-3005 | B6: W-1003 | C6: =IFERROR(VLOOKUP(B6,Workers!$A:$H,2,FALSE),"") | D6: J-2003 | E6: =IFERROR(VLOOKUP(D6,Jobs!$A:$G,2,FALSE),"") | F6: 46178 | G6: 0.35416667 | H6: 0.52083333 | I6: 0 | J6: =IF(OR(G6="",H6=""),"",MAX(0,(H6-G6)*24-(I6/60))) | K6: =IFERROR(VLOOKUP(D6,Jobs!$A:$G,5,FALSE),"") | L6: =IF(OR(J6="",K6=""),"",J6*K6) | M6: 15 | N6: 0 | O6: =IF(L6="","",L6+M6-N6) | P6: Finalized | Q6: 46178.531 | R6: 46179.385 | S6: Visible correction: added reimbursement before worker was inactive. | T6: Historical reimbursement correction retained.
C7: =IFERROR(VLOOKUP(B7,Workers!$A:$H,2,FALSE),"") | E7: =IFERROR(VLOOKUP(D7,Jobs!$A:$G,2,FALSE),"") | J7: =IF(OR(G7="",H7=""),"",MAX(0,(H7-G7)*24-(I7/60))) | K7: =IFERROR(VLOOKUP(D7,Jobs!$A:$G,5,FALSE),"") | L7: =IF(OR(J7="",K7=""),"",J7*K7) | O7: =IF(L7="","",L7+M7-N7)
C8: =IFERROR(VLOOKUP(B8,Workers!$A:$H,2,FALSE),"") | E8: =IFERROR(VLOOKUP(D8,Jobs!$A:$G,2,FALSE),"") | J8: =IF(OR(G8="",H8=""),"",MAX(0,(H8-G8)*24-(I8/60))) | K8: =IFERROR(VLOOKUP(D8,Jobs!$A:$G,5,FALSE),"") | L8: =IF(OR(J8="",K8=""),"",J8*K8) | O8: =IF(L8="","",L8+M8-N8)
C9: =IFERROR(VLOOKUP(B9,Workers!$A:$H,2,FALSE),"") | E9: =IFERROR(VLOOKUP(D9,Jobs!$A:$G,2,FALSE),"") | J9: =IF(OR(G9="",H9=""),"",MAX(0,(H9-G9)*24-(I9/60))) | K9: =IFERROR(VLOOKUP(D9,Jobs!$A:$G,5,FALSE),"") | L9: =IF(OR(J9="",K9=""),"",J9*K9) | O9: =IF(L9="","",L9+M9-N9)
C10: =IFERROR(VLOOKUP(B10,Workers!$A:$H,2,FALSE),"") | E10: =IFERROR(VLOOKUP(D10,Jobs!$A:$G,2,FALSE),"") | J10: =IF(OR(G10="",H10=""),"",MAX(0,(H10-G10)*24-(I10/60))) | K10: =IFERROR(VLOOKUP(D10,Jobs!$A:$G,5,FALSE),"") | L10: =IF(OR(J10="",K10=""),"",J10*K10) | O10: =IF(L10="","",L10+M10-N10)
C11: =IFERROR(VLOOKUP(B11,Workers!$A:$H,2,FALSE),"") | E11: =IFERROR(VLOOKUP(D11,Jobs!$A:$G,2,FALSE),"") | J11: =IF(OR(G11="",H11=""),"",MAX(0,(H11-G11)*24-(I11/60))) | K11: =IFERROR(VLOOKUP(D11,Jobs!$A:$G,5,FALSE),"") | L11: =IF(OR(J11="",K11=""),"",J11*K11) | O11: =IF(L11="","",L11+M11-N11)
C12: =IFERROR(VLOOKUP(B12,Workers!$A:$H,2,FALSE),"") | E12: =IFERROR(VLOOKUP(D12,Jobs!$A:$G,2,FALSE),"") | J12: =IF(OR(G12="",H12=""),"",MAX(0,(H12-G12)*24-(I12/60))) | K12: =IFERROR(VLOOKUP(D12,Jobs!$A:$G,5,FALSE),"") | L12: =IF(OR(J12="",K12=""),"",J12*K12) | O12: =IF(L12="","",L12+M12-N12)
C13: =IFERROR(VLOOKUP(B13,Workers!$A:$H,2,FALSE),"") | E13: =IFERROR(VLOOKUP(D13,Jobs!$A:$G,2,FALSE),"") | J13: =IF(OR(G13="",H13=""),"",MAX(0,(H13-G13)*24-(I13/60))) | K13: =IFERROR(VLOOKUP(D13,Jobs!$A:$G,5,FALSE),"") | L13: =IF(OR(J13="",K13=""),"",J13*K13) | O13: =IF(L13="","",L13+M13-N13)
C14: =IFERROR(VLOOKUP(B14,Workers!$A:$H,2,FALSE),"") | E14: =IFERROR(VLOOKUP(D14,Jobs!$A:$G,2,FALSE),"") | J14: =IF(OR(G14="",H14=""),"",MAX(0,(H14-G14)*24-(I14/60))) | K14: =IFERROR(VLOOKUP(D14,Jobs!$A:$G,5,FALSE),"") | L14: =IF(OR(J14="",K14=""),"",J14*K14) | O14: =IF(L14="","",L14+M14-N14)
C15: =IFERROR(VLOOKUP(B15,Workers!$A:$H,2,FALSE),"") | E15: =IFERROR(VLOOKUP(D15,Jobs!$A:$G,2,FALSE),"") | J15: =IF(OR(G15="",H15=""),"",MAX(0,(H15-G15)*24-(I15/60))) | K15: =IFERROR(VLOOKUP(D15,Jobs!$A:$G,5,FALSE),"") | L15: =IF(OR(J15="",K15=""),"",J15*K15) | O15: =IF(L15="","",L15+M15-N15)
C16: =IFERROR(VLOOKUP(B16,Workers!$A:$H,2,FALSE),"") | E16: =IFERROR(VLOOKUP(D16,Jobs!$A:$G,2,FALSE),"") | J16: =IF(OR(G16="",H16=""),"",MAX(0,(H16-G16)*24-(I16/60))) | K16: =IFERROR(VLOOKUP(D16,Jobs!$A:$G,5,FALSE),"") | L16: =IF(OR(J16="",K16=""),"",J16*K16) | O16: =IF(L16="","",L16+M16-N16)
C17: =IFERROR(VLOOKUP(B17,Workers!$A:$H,2,FALSE),"") | E17: =IFERROR(VLOOKUP(D17,Jobs!$A:$G,2,FALSE),"") | J17: =IF(OR(G17="",H17=""),"",MAX(0,(H17-G17)*24-(I17/60))) | K17: =IFERROR(VLOOKUP(D17,Jobs!$A:$G,5,FALSE),"") | L17: =IF(OR(J17="",K17=""),"",J17*K17) | O17: =IF(L17="","",L17+M17-N17)
C18: =IFERROR(VLOOKUP(B18,Workers!$A:$H,2,FALSE),"") | E18: =IFERROR(VLOOKUP(D18,Jobs!$A:$G,2,FALSE),"") | J18: =IF(OR(G18="",H18=""),"",MAX(0,(H18-G18)*24-(I18/60))) | K18: =IFERROR(VLOOKUP(D18,Jobs!$A:$G,5,FALSE),"") | L18: =IF(OR(J18="",K18=""),"",J18*K18) | O18: =IF(L18="","",L18+M18-N18)
... C200: =IFERROR(VLOOKUP(B200,Workers!$A:$H,2,FALSE),"") | E200: =IFERROR(VLOOKUP(D200,Jobs!$A:$G,2,FALSE),"") | J200: =IF(OR(G200="",H200=""),"",MAX(0,(H200-G200)*24-(I200/60))) | K200: =IFERROR(VLOOKUP(D200,Jobs!$A:$G,5,FALSE),"") | L200: =IF(OR(J200="",K200=""),"",J200*K200) | O200: =IF(L200="","",L200+M200-N200)

Sheet Pay Periods
A1: Pay Period ID | B1: Worker ID | C1: Worker Name | D1: Period Start | E1: Period End | F1: Status | G1: Payment Status | H1: Total Hours | I1: Gross Pay | J1: Reimbursement Total | K1: Deduction Total | L1: Net Pay | M1: Finalized At | N1: Paid At | O1: Notes | Q1: Pay Period | S1: Approved Hours
A2: P-4001 | B2: W-1001 | C2: =IFERROR(VLOOKUP(B2,Workers!$A:$H,2,FALSE),"") | D2: 46174 | E2: 46180 | F2: Paid | G2: Paid | H2: =SUMIFS('Time Entries'!$J:$J,'Time Entries'!$B:$B,$B2,'Time Entries'!$F:$F,">="&$D2,'Time Entries'!$F:$F,"<="&$E2,'Time Entries'!$P:$P,"<>Draft",'Time Entries'!$P:$P,"<>Rejected") | I2: =SUMIFS('Time Entries'!$L:$L,'Time Entries'!$B:$B,$B2,'Time Entries'!$F:$F,">="&$D2,'Time Entries'!$F:$F,"<="&$E2,'Time Entries'!$P:$P,"<>Draft",'Time Entries'!$P:$P,"<>Rejected") | J2: =SUMIFS('Time Entries'!$M:$M,'Time Entries'!$B:$B,$B2,'Time Entries'!$F:$F,">="&$D2,'Time Entries'!$F:$F,"<="&$E2,'Time Entries'!$P:$P,"<>Draft",'Time Entries'!$P:$P,"<>Rejected") | K2: =SUMIFS('Time Entries'!$N:$N,'Time Entries'!$B:$B,$B2,'Time Entries'!$F:$F,">="&$D2,'Time Entries'!$F:$F,"<="&$E2,'Time Entries'!$P:$P,"<>Draft",'Time Entries'!$P:$P,"<>Rejected") | L2: =I2+J2-K2 | M2: 46180.417 | N2: 46181.5 | O2: Paid worker proof can be regenerated. | Q2: =IFERROR(INDEX($A$2:$A$100,MATCH("Open",$F$2:$F$100,0)),"Demo") | S2: =SUM($H$2:$H$100)
A3: P-4002 | B3: W-1002 | C3: =IFERROR(VLOOKUP(B3,Workers!$A:$H,2,FALSE),"") | D3: 46174 | E3: 46180 | F3: Open | G3: Unpaid | H3: =SUMIFS('Time Entries'!$J:$J,'Time Entries'!$B:$B,$B3,'Time Entries'!$F:$F,">="&$D3,'Time Entries'!$F:$F,"<="&$E3,'Time Entries'!$P:$P,"<>Draft",'Time Entries'!$P:$P,"<>Rejected") | I3: =SUMIFS('Time Entries'!$L:$L,'Time Entries'!$B:$B,$B3,'Time Entries'!$F:$F,">="&$D3,'Time Entries'!$F:$F,"<="&$E3,'Time Entries'!$P:$P,"<>Draft",'Time Entries'!$P:$P,"<>Rejected") | J3: =SUMIFS('Time Entries'!$M:$M,'Time Entries'!$B:$B,$B3,'Time Entries'!$F:$F,">="&$D3,'Time Entries'!$F:$F,"<="&$E3,'Time Entries'!$P:$P,"<>Draft",'Time Entries'!$P:$P,"<>Rejected") | K3: =SUMIFS('Time Entries'!$N:$N,'Time Entries'!$B:$B,$B3,'Time Entries'!$F:$F,">="&$D3,'Time Entries'!$F:$F,"<="&$E3,'Time Entries'!$P:$P,"<>Draft",'Time Entries'!$P:$P,"<>Rejected") | L3: =I3+J3-K3 | O3: Open period with submitted entry.
A4: P-4003 | B4: W-1003 | C4: =IFERROR(VLOOKUP(B4,Workers!$A:$H,2,FALSE),"") | D4: 46174 | E4: 46180 | F4: Finalized | G4: Unpaid | H4: =SUMIFS('Time Entries'!$J:$J,'Time Entries'!$B:$B,$B4,'Time Entries'!$F:$F,">="&$D4,'Time Entries'!$F:$F,"<="&$E4,'Time Entries'!$P:$P,"<>Draft",'Time Entries'!$P:$P,"<>Rejected") | I4: =SUMIFS('Time Entries'!$L:$L,'Time Entries'!$B:$B,$B4,'Time Entries'!$F:$F,">="&$D4,'Time Entries'!$F:$F,"<="&$E4,'Time Entries'!$P:$P,"<>Draft",'Time Entries'!$P:$P,"<>Rejected") | J4: =SUMIFS('Time Entries'!$M:$M,'Time Entries'!$B:$B,$B4,'Time Entries'!$F:$F,">="&$D4,'Time Entries'!$F:$F,"<="&$E4,'Time Entries'!$P:$P,"<>Draft",'Time Entries'!$P:$P,"<>Rejected") | K4: =SUMIFS('Time Entries'!$N:$N,'Time Entries'!$B:$B,$B4,'Time Entries'!$F:$F,">="&$D4,'Time Entries'!$F:$F,"<="&$E4,'Time Entries'!$P:$P,"<>Draft",'Time Entries'!$P:$P,"<>Rejected") | L4: =I4+J4-K4 | M4: 46181.375 | O4: Inactive worker history remains visible and provable. | Q4: Worker Count | S4: Paid Status
C5: =IFERROR(VLOOKUP(B5,Workers!$A:$H,2,FALSE),"") | H5: =SUMIFS('Time Entries'!$J:$J,'Time Entries'!$B:$B,$B5,'Time Entries'!$F:$F,">="&$D5,'Time Entries'!$F:$F,"<="&$E5,'Time Entries'!$P:$P,"<>Draft",'Time Entries'!$P:$P,"<>Rejected") | I5: =SUMIFS('Time Entries'!$L:$L,'Time Entries'!$B:$B,$B5,'Time Entries'!$F:$F,">="&$D5,'Time Entries'!$F:$F,"<="&$E5,'Time Entries'!$P:$P,"<>Draft",'Time Entries'!$P:$P,"<>Rejected") | J5: =SUMIFS('Time Entries'!$M:$M,'Time Entries'!$B:$B,$B5,'Time Entries'!$F:$F,">="&$D5,'Time Entries'!$F:$F,"<="&$E5,'Time Entries'!$P:$P,"<>Draft",'Time Entries'!$P:$P,"<>Rejected") | K5: =SUMIFS('Time Entries'!$N:$N,'Time Entries'!$B:$B,$B5,'Time Entries'!$F:$F,">="&$D5,'Time Entries'!$F:$F,"<="&$E5,'Time Entries'!$P:$P,"<>Draft",'Time Entries'!$P:$P,"<>Rejected") | L5: =I5+J5-K5 | Q5: =COUNTA(UNIQUE($B$2:$B$100)) | S5: =COUNTIF($G$2:$G$100,"Paid")&" paid"
C6: =IFERROR(VLOOKUP(B6,Workers!$A:$H,2,FALSE),"") | H6: =SUMIFS('Time Entries'!$J:$J,'Time Entries'!$B:$B,$B6,'Time Entries'!$F:$F,">="&$D6,'Time Entries'!$F:$F,"<="&$E6,'Time Entries'!$P:$P,"<>Draft",'Time Entries'!$P:$P,"<>Rejected") | I6: =SUMIFS('Time Entries'!$L:$L,'Time Entries'!$B:$B,$B6,'Time Entries'!$F:$F,">="&$D6,'Time Entries'!$F:$F,"<="&$E6,'Time Entries'!$P:$P,"<>Draft",'Time Entries'!$P:$P,"<>Rejected") | J6: =SUMIFS('Time Entries'!$M:$M,'Time Entries'!$B:$B,$B6,'Time Entries'!$F:$F,">="&$D6,'Time Entries'!$F:$F,"<="&$E6,'Time Entries'!$P:$P,"<>Draft",'Time Entries'!$P:$P,"<>Rejected") | K6: =SUMIFS('Time Entries'!$N:$N,'Time Entries'!$B:$B,$B6,'Time Entries'!$F:$F,">="&$D6,'Time Entries'!$F:$F,"<="&$E6,'Time Entries'!$P:$P,"<>Draft",'Time Entries'!$P:$P,"<>Rejected") | L6: =I6+J6-K6
C7: =IFERROR(VLOOKUP(B7,Workers!$A:$H,2,FALSE),"") | H7: =SUMIFS('Time Entries'!$J:$J,'Time Entries'!$B:$B,$B7,'Time Entries'!$F:$F,">="&$D7,'Time Entries'!$F:$F,"<="&$E7,'Time Entries'!$P:$P,"<>Draft",'Time Entries'!$P:$P,"<>Rejected") | I7: =SUMIFS('Time Entries'!$L:$L,'Time Entries'!$B:$B,$B7,'Time Entries'!$F:$F,">="&$D7,'Time Entries'!$F:$F,"<="&$E7,'Time Entries'!$P:$P,"<>Draft",'Time Entries'!$P:$P,"<>Rejected") | J7: =SUMIFS('Time Entries'!$M:$M,'Time Entries'!$B:$B,$B7,'Time Entries'!$F:$F,">="&$D7,'Time Entries'!$F:$F,"<="&$E7,'Time Entries'!$P:$P,"<>Draft",'Time Entries'!$P:$P,"<>Rejected") | K7: =SUMIFS('Time Entries'!$N:$N,'Time Entries'!$B:$B,$B7,'Time Entries'!$F:$F,">="&$D7,'Time Entries'!$F:$F,"<="&$E7,'Time Entries'!$P:$P,"<>Draft",'Time Entries'!$P:$P,"<>Rejected") | L7: =I7+J7-K7 | Q7: Export Batch ID
C8: =IFERROR(VLOOKUP(B8,Workers!$A:$H,2,FALSE),"") | H8: =SUMIFS('Time Entries'!$J:$J,'Time Entries'!$B:$B,$B8,'Time Entries'!$F:$F,">="&$D8,'Time Entries'!$F:$F,"<="&$E8,'Time Entries'!$P:$P,"<>Draft",'Time Entries'!$P:$P,"<>Rejected") | I8: =SUMIFS('Time Entries'!$L:$L,'Time Entries'!$B:$B,$B8,'Time Entries'!$F:$F,">="&$D8,'Time Entries'!$F:$F,"<="&$E8,'Time Entries'!$P:$P,"<>Draft",'Time Entries'!$P:$P,"<>Rejected") | J8: =SUMIFS('Time Entries'!$M:$M,'Time Entries'!$B:$B,$B8,'Time Entries'!$F:$F,">="&$D8,'Time Entries'!$F:$F,"<="&$E8,'Time Entries'!$P:$P,"<>Draft",'Time Entries'!$P:$P,"<>Rejected") | K8: =SUMIFS('Time Entries'!$N:$N,'Time Entries'!$B:$B,$B8,'Time Entries'!$F:$F,">="&$D8,'Time Entries'!$F:$F,"<="&$E8,'Time Entries'!$P:$P,"<>Draft",'Time Entries'!$P:$P,"<>Rejected") | L8: =I8+J8-K8 | Q8: =IFERROR(INDEX('Proof Exports'!$A$2:$A$100,1),"No export")
C9: =IFERROR(VLOOKUP(B9,Workers!$A:$H,2,FALSE),"") | H9: =SUMIFS('Time Entries'!$J:$J,'Time Entries'!$B:$B,$B9,'Time Entries'!$F:$F,">="&$D9,'Time Entries'!$F:$F,"<="&$E9,'Time Entries'!$P:$P,"<>Draft",'Time Entries'!$P:$P,"<>Rejected") | I9: =SUMIFS('Time Entries'!$L:$L,'Time Entries'!$B:$B,$B9,'Time Entries'!$F:$F,">="&$D9,'Time Entries'!$F:$F,"<="&$E9,'Time Entries'!$P:$P,"<>Draft",'Time Entries'!$P:$P,"<>Rejected") | J9: =SUMIFS('Time Entries'!$M:$M,'Time Entries'!$B:$B,$B9,'Time Entries'!$F:$F,">="&$D9,'Time Entries'!$F:$F,"<="&$E9,'Time Entries'!$P:$P,"<>Draft",'Time Entries'!$P:$P,"<>Rejected") | K9: =SUMIFS('Time Entries'!$N:$N,'Time Entries'!$B:$B,$B9,'Time Entries'!$F:$F,">="&$D9,'Time Entries'!$F:$F,"<="&$E9,'Time Entries'!$P:$P,"<>Draft",'Time Entries'!$P:$P,"<>Rejected") | L9: =I9+J9-K9
C10: =IFERROR(VLOOKUP(B10,Workers!$A:$H,2,FALSE),"") | H10: =SUMIFS('Time Entries'!$J:$J,'Time Entries'!$B:$B,$B10,'Time Entries'!$F:$F,">="&$D10,'Time Entries'!$F:$F,"<="&$E10,'Time Entries'!$P:$P,"<>Draft",'Time Entries'!$P:$P,"<>Rejected") | I10: =SUMIFS('Time Entries'!$L:$L,'Time Entries'!$B:$B,$B10,'Time Entries'!$F:$F,">="&$D10,'Time Entries'!$F:$F,"<="&$E10,'Time Entries'!$P:$P,"<>Draft",'Time Entries'!$P:$P,"<>Rejected") | J10: =SUMIFS('Time Entries'!$M:$M,'Time Entries'!$B:$B,$B10,'Time Entries'!$F:$F,">="&$D10,'Time Entries'!$F:$F,"<="&$E10,'Time Entries'!$P:$P,"<>Draft",'Time Entries'!$P:$P,"<>Rejected") | K10: =SUMIFS('Time Entries'!$N:$N,'Time Entries'!$B:$B,$B10,'Time Entries'!$F:$F,">="&$D10,'Time Entries'!$F:$F,"<="&$E10,'Time Entries'!$P:$P,"<>Draft",'Time Entries'!$P:$P,"<>Rejected") | L10: =I10+J10-K10
C11: =IFERROR(VLOOKUP(B11,Workers!$A:$H,2,FALSE),"") | H11: =SUMIFS('Time Entries'!$J:$J,'Time Entries'!$B:$B,$B11,'Time Entries'!$F:$F,">="&$D11,'Time Entries'!$F:$F,"<="&$E11,'Time Entries'!$P:$P,"<>Draft",'Time Entries'!$P:$P,"<>Rejected") | I11: =SUMIFS('Time Entries'!$L:$L,'Time Entries'!$B:$B,$B11,'Time Entries'!$F:$F,">="&$D11,'Time Entries'!$F:$F,"<="&$E11,'Time Entries'!$P:$P,"<>Draft",'Time Entries'!$P:$P,"<>Rejected") | J11: =SUMIFS('Time Entries'!$M:$M,'Time Entries'!$B:$B,$B11,'Time Entries'!$F:$F,">="&$D11,'Time Entries'!$F:$F,"<="&$E11,'Time Entries'!$P:$P,"<>Draft",'Time Entries'!$P:$P,"<>Rejected") | K11: =SUMIFS('Time Entries'!$N:$N,'Time Entries'!$B:$B,$B11,'Time Entries'!$F:$F,">="&$D11,'Time Entries'!$F:$F,"<="&$E11,'Time Entries'!$P:$P,"<>Draft",'Time Entries'!$P:$P,"<>Rejected") | L11: =I11+J11-K11
C12: =IFERROR(VLOOKUP(B12,Workers!$A:$H,2,FALSE),"") | H12: =SUMIFS('Time Entries'!$J:$J,'Time Entries'!$B:$B,$B12,'Time Entries'!$F:$F,">="&$D12,'Time Entries'!$F:$F,"<="&$E12,'Time Entries'!$P:$P,"<>Draft",'Time Entries'!$P:$P,"<>Rejected") | I12: =SUMIFS('Time Entries'!$L:$L,'Time Entries'!$B:$B,$B12,'Time Entries'!$F:$F,">="&$D12,'Time Entries'!$F:$F,"<="&$E12,'Time Entries'!$P:$P,"<>Draft",'Time Entries'!$P:$P,"<>Rejected") | J12: =SUMIFS('Time Entries'!$M:$M,'Time Entries'!$B:$B,$B12,'Time Entries'!$F:$F,">="&$D12,'Time Entries'!$F:$F,"<="&$E12,'Time Entries'!$P:$P,"<>Draft",'Time Entries'!$P:$P,"<>Rejected") | K12: =SUMIFS('Time Entries'!$N:$N,'Time Entries'!$B:$B,$B12,'Time Entries'!$F:$F,">="&$D12,'Time Entries'!$F:$F,"<="&$E12,'Time Entries'!$P:$P,"<>Draft",'Time Entries'!$P:$P,"<>Rejected") | L12: =I12+J12-K12
C13: =IFERROR(VLOOKUP(B13,Workers!$A:$H,2,FALSE),"") | H13: =SUMIFS('Time Entries'!$J:$J,'Time Entries'!$B:$B,$B13,'Time Entries'!$F:$F,">="&$D13,'Time Entries'!$F:$F,"<="&$E13,'Time Entries'!$P:$P,"<>Draft",'Time Entries'!$P:$P,"<>Rejected") | I13: =SUMIFS('Time Entries'!$L:$L,'Time Entries'!$B:$B,$B13,'Time Entries'!$F:$F,">="&$D13,'Time Entries'!$F:$F,"<="&$E13,'Time Entries'!$P:$P,"<>Draft",'Time Entries'!$P:$P,"<>Rejected") | J13: =SUMIFS('Time Entries'!$M:$M,'Time Entries'!$B:$B,$B13,'Time Entries'!$F:$F,">="&$D13,'Time Entries'!$F:$F,"<="&$E13,'Time Entries'!$P:$P,"<>Draft",'Time Entries'!$P:$P,"<>Rejected") | K13: =SUMIFS('Time Entries'!$N:$N,'Time Entries'!$B:$B,$B13,'Time Entries'!$F:$F,">="&$D13,'Time Entries'!$F:$F,"<="&$E13,'Time Entries'!$P:$P,"<>Draft",'Time Entries'!$P:$P,"<>Rejected") | L13: =I13+J13-K13
C14: =IFERROR(VLOOKUP(B14,Workers!$A:$H,2,FALSE),"") | H14: =SUMIFS('Time Entries'!$J:$J,'Time Entries'!$B:$B,$B14,'Time Entries'!$F:$F,">="&$D14,'Time Entries'!$F:$F,"<="&$E14,'Time Entries'!$P:$P,"<>Draft",'Time Entries'!$P:$P,"<>Rejected") | I14: =SUMIFS('Time Entries'!$L:$L,'Time Entries'!$B:$B,$B14,'Time Entries'!$F:$F,">="&$D14,'Time Entries'!$F:$F,"<="&$E14,'Time Entries'!$P:$P,"<>Draft",'Time Entries'!$P:$P,"<>Rejected") | J14: =SUMIFS('Time Entries'!$M:$M,'Time Entries'!$B:$B,$B14,'Time Entries'!$F:$F,">="&$D14,'Time Entries'!$F:$F,"<="&$E14,'Time Entries'!$P:$P,"<>Draft",'Time Entries'!$P:$P,"<>Rejected") | K14: =SUMIFS('Time Entries'!$N:$N,'Time Entries'!$B:$B,$B14,'Time Entries'!$F:$F,">="&$D14,'Time Entries'!$F:$F,"<="&$E14,'Time Entries'!$P:$P,"<>Draft",'Time Entries'!$P:$P,"<>Rejected") | L14: =I14+J14-K14
C15: =IFERROR(VLOOKUP(B15,Workers!$A:$H,2,FALSE),"") | H15: =SUMIFS('Time Entries'!$J:$J,'Time Entries'!$B:$B,$B15,'Time Entries'!$F:$F,">="&$D15,'Time Entries'!$F:$F,"<="&$E15,'Time Entries'!$P:$P,"<>Draft",'Time Entries'!$P:$P,"<>Rejected") | I15: =SUMIFS('Time Entries'!$L:$L,'Time Entries'!$B:$B,$B15,'Time Entries'!$F:$F,">="&$D15,'Time Entries'!$F:$F,"<="&$E15,'Time Entries'!$P:$P,"<>Draft",'Time Entries'!$P:$P,"<>Rejected") | J15: =SUMIFS('Time Entries'!$M:$M,'Time Entries'!$B:$B,$B15,'Time Entries'!$F:$F,">="&$D15,'Time Entries'!$F:$F,"<="&$E15,'Time Entries'!$P:$P,"<>Draft",'Time Entries'!$P:$P,"<>Rejected") | K15: =SUMIFS('Time Entries'!$N:$N,'Time Entries'!$B:$B,$B15,'Time Entries'!$F:$F,">="&$D15,'Time Entries'!$F:$F,"<="&$E15,'Time Entries'!$P:$P,"<>Draft",'Time Entries'!$P:$P,"<>Rejected") | L15: =I15+J15-K15
C16: =IFERROR(VLOOKUP(B16,Workers!$A:$H,2,FALSE),"") | H16: =SUMIFS('Time Entries'!$J:$J,'Time Entries'!$B:$B,$B16,'Time Entries'!$F:$F,">="&$D16,'Time Entries'!$F:$F,"<="&$E16,'Time Entries'!$P:$P,"<>Draft",'Time Entries'!$P:$P,"<>Rejected") | I16: =SUMIFS('Time Entries'!$L:$L,'Time Entries'!$B:$B,$B16,'Time Entries'!$F:$F,">="&$D16,'Time Entries'!$F:$F,"<="&$E16,'Time Entries'!$P:$P,"<>Draft",'Time Entries'!$P:$P,"<>Rejected") | J16: =SUMIFS('Time Entries'!$M:$M,'Time Entries'!$B:$B,$B16,'Time Entries'!$F:$F,">="&$D16,'Time Entries'!$F:$F,"<="&$E16,'Time Entries'!$P:$P,"<>Draft",'Time Entries'!$P:$P,"<>Rejected") | K16: =SUMIFS('Time Entries'!$N:$N,'Time Entries'!$B:$B,$B16,'Time Entries'!$F:$F,">="&$D16,'Time Entries'!$F:$F,"<="&$E16,'Time Entries'!$P:$P,"<>Draft",'Time Entries'!$P:$P,"<>Rejected") | L16: =I16+J16-K16
C17: =IFERROR(VLOOKUP(B17,Workers!$A:$H,2,FALSE),"") | H17: =SUMIFS('Time Entries'!$J:$J,'Time Entries'!$B:$B,$B17,'Time Entries'!$F:$F,">="&$D17,'Time Entries'!$F:$F,"<="&$E17,'Time Entries'!$P:$P,"<>Draft",'Time Entries'!$P:$P,"<>Rejected") | I17: =SUMIFS('Time Entries'!$L:$L,'Time Entries'!$B:$B,$B17,'Time Entries'!$F:$F,">="&$D17,'Time Entries'!$F:$F,"<="&$E17,'Time Entries'!$P:$P,"<>Draft",'Time Entries'!$P:$P,"<>Rejected") | J17: =SUMIFS('Time Entries'!$M:$M,'Time Entries'!$B:$B,$B17,'Time Entries'!$F:$F,">="&$D17,'Time Entries'!$F:$F,"<="&$E17,'Time Entries'!$P:$P,"<>Draft",'Time Entries'!$P:$P,"<>Rejected") | K17: =SUMIFS('Time Entries'!$N:$N,'Time Entries'!$B:$B,$B17,'Time Entries'!$F:$F,">="&$D17,'Time Entries'!$F:$F,"<="&$E17,'Time Entries'!$P:$P,"<>Draft",'Time Entries'!$P:$P,"<>Rejected") | L17: =I17+J17-K17
C18: =IFERROR(VLOOKUP(B18,Workers!$A:$H,2,FALSE),"") | H18: =SUMIFS('Time Entries'!$J:$J,'Time Entries'!$B:$B,$B18,'Time Entries'!$F:$F,">="&$D18,'Time Entries'!$F:$F,"<="&$E18,'Time Entries'!$P:$P,"<>Draft",'Time Entries'!$P:$P,"<>Rejected") | I18: =SUMIFS('Time Entries'!$L:$L,'Time Entries'!$B:$B,$B18,'Time Entries'!$F:$F,">="&$D18,'Time Entries'!$F:$F,"<="&$E18,'Time Entries'!$P:$P,"<>Draft",'Time Entries'!$P:$P,"<>Rejected") | J18: =SUMIFS('Time Entries'!$M:$M,'Time Entries'!$B:$B,$B18,'Time Entries'!$F:$F,">="&$D18,'Time Entries'!$F:$F,"<="&$E18,'Time Entries'!$P:$P,"<>Draft",'Time Entries'!$P:$P,"<>Rejected") | K18: =SUMIFS('Time Entries'!$N:$N,'Time Entries'!$B:$B,$B18,'Time Entries'!$F:$F,">="&$D18,'Time Entries'!$F:$F,"<="&$E18,'Time Entries'!$P:$P,"<>Draft",'Time Entries'!$P:$P,"<>Rejected") | L18: =I18+J18-K18
C19: =IFERROR(VLOOKUP(B19,Workers!$A:$H,2,FALSE),"") | H19: =SUMIFS('Time Entries'!$J:$J,'Time Entries'!$B:$B,$B19,'Time Entries'!$F:$F,">="&$D19,'Time Entries'!$F:$F,"<="&$E19,'Time Entries'!$P:$P,"<>Draft",'Time Entries'!$P:$P,"<>Rejected") | I19: =SUMIFS('Time Entries'!$L:$L,'Time Entries'!$B:$B,$B19,'Time Entries'!$F:$F,">="&$D19,'Time Entries'!$F:$F,"<="&$E19,'Time Entries'!$P:$P,"<>Draft",'Time Entries'!$P:$P,"<>Rejected") | J19: =SUMIFS('Time Entries'!$M:$M,'Time Entries'!$B:$B,$B19,'Time Entries'!$F:$F,">="&$D19,'Time Entries'!$F:$F,"<="&$E19,'Time Entries'!$P:$P,"<>Draft",'Time Entries'!$P:$P,"<>Rejected") | K19: =SUMIFS('Time Entries'!$N:$N,'Time Entries'!$B:$B,$B19,'Time Entries'!$F:$F,">="&$D19,'Time Entries'!$F:$F,"<="&$E19,'Time Entries'!$P:$P,"<>Draft",'Time Entries'!$P:$P,"<>Rejected") | L19: =I19+J19-K19
C20: =IFERROR(VLOOKUP(B20,Workers!$A:$H,2,FALSE),"") | H20: =SUMIFS('Time Entries'!$J:$J,'Time Entries'!$B:$B,$B20,'Time Entries'!$F:$F,">="&$D20,'Time Entries'!$F:$F,"<="&$E20,'Time Entries'!$P:$P,"<>Draft",'Time Entries'!$P:$P,"<>Rejected") | I20: =SUMIFS('Time Entries'!$L:$L,'Time Entries'!$B:$B,$B20,'Time Entries'!$F:$F,">="&$D20,'Time Entries'!$F:$F,"<="&$E20,'Time Entries'!$P:$P,"<>Draft",'Time Entries'!$P:$P,"<>Rejected") | J20: =SUMIFS('Time Entries'!$M:$M,'Time Entries'!$B:$B,$B20,'Time Entries'!$F:$F,">="&$D20,'Time Entries'!$F:$F,"<="&$E20,'Time Entries'!$P:$P,"<>Draft",'Time Entries'!$P:$P,"<>Rejected") | K20: =SUMIFS('Time Entries'!$N:$N,'Time Entries'!$B:$B,$B20,'Time Entries'!$F:$F,">="&$D20,'Time Entries'!$F:$F,"<="&$E20,'Time Entries'!$P:$P,"<>Draft",'Time Entries'!$P:$P,"<>Rejected") | L20: =I20+J20-K20
... C100: =IFERROR(VLOOKUP(B100,Workers!$A:$H,2,FALSE),"") | H100: =SUMIFS('Time Entries'!$J:$J,'Time Entries'!$B:$B,$B100,'Time Entries'!$F:$F,">="&$D100,'Time Entries'!$F:$F,"<="&$E100,'Time Entries'!$P:$P,"<>Draft",'Time Entries'!$P:$P,"<>Rejected") | I100: =SUMIFS('Time Entries'!$L:$L,'Time Entries'!$B:$B,$B100,'Time Entries'!$F:$F,">="&$D100,'Time Entries'!$F:$F,"<="&$E100,'Time Entries'!$P:$P,"<>Draft",'Time Entries'!$P:$P,"<>Rejected") | J100: =SUMIFS('Time Entries'!$M:$M,'Time Entries'!$B:$B,$B100,'Time Entries'!$F:$F,">="&$D100,'Time Entries'!$F:$F,"<="&$E100,'Time Entries'!$P:$P,"<>Draft",'Time Entries'!$P:$P,"<>Rejected") | K100: =SUMIFS('Time Entries'!$N:$N,'Time Entries'!$B:$B,$B100,'Time Entries'!$F:$F,">="&$D100,'Time Entries'!$F:$F,"<="&$E100,'Time Entries'!$P:$P,"<>Draft",'Time Entries'!$P:$P,"<>Rejected") | L100: =I100+J100-K100

Sheet Worker Proof
A1: CrewPay Ledger Worker Proof
A2: Printable selected-worker proof packet. Use one Worker ID and one Pay Period ID only.
A3: Selected Worker ID | B3: W-1001 | D3: Proof Status | E3: =IF($B$10="OK - worker/pay period match","Ready for export","Check selector")
A4: Selected Pay Period ID | B4: P-4001 | D4: Export Batch | E4: =IFERROR(INDEX('Proof Exports'!$A$2:$A$100,MATCH($B$4,'Proof Exports'!$D$2:$D$100,0)),"Not exported")
A5: Worker Name | B5: =IFERROR(VLOOKUP($B$3,Workers!$A:$H,2,FALSE),"") | D5: Paid Date | E5: =IFERROR(VLOOKUP($B$4,'Pay Periods'!$A:$O,14,FALSE),"")
A6: Worker Status | B6: =IFERROR(VLOOKUP($B$3,Workers!$A:$H,5,FALSE),"") | D6: Archive Rule | E6: Inactive workers keep historical proof.
A7: Date Range | B7: =IFERROR(TEXT(VLOOKUP($B$4,'Pay Periods'!$A:$O,4,FALSE),"m/d/yyyy")&" to "&TEXT(VLOOKUP($B$4,'Pay Periods'!$A:$O,5,FALSE),"m/d/yyyy"),"")
A8: Payment Status | B8: =IFERROR(VLOOKUP($B$4,'Pay Periods'!$A:$O,7,FALSE),"") | D8: Correction / Dispute Notes | I8: Read-only Archive Note
A9: Generated Timestamp | B9: =NOW() | D9: =IFERROR(TEXTJOIN(CHAR(10),TRUE,FILTER('Correction Log'!$H$2:$H$100,'Correction Log'!$C$2:$C$100=$B$3,'Correction Log'!$E$2:$E$100=$B$4)),"No correction notes for selected proof.") | I9: Former or inactive workers can keep proof access for historical records, but should not receive new time entries.
A10: Proof Selector Check | B10: =IFERROR(IF(VLOOKUP($B$4,'Pay Periods'!$A:$O,2,FALSE)=$B$3,"OK - worker/pay period match","CHECK SELECTION - pay period belongs to another worker"),"CHECK SELECTION")
A12: Entry ID | B12: Work Date | C12: Job ID | D12: Job Name | E12: Hours | F12: Rate | G12: Gross Pay | H12: Reimbursement | I12: Deduction | J12: Net Pay | K12: Approval Status | L12: Correction Note | M12: Notes
A13: =IF($B$10<>"OK - worker/pay period match","Check selected worker/pay period before printing proof",FILTER({'Time Entries'!A2:A200,'Time Entries'!F2:F200,'Time Entries'!D2:D200,'Time Entries'!E2:E200,'Time Entries'!J2:J200,'Time Entries'!K2:K200,'Time Entries'!L2:L200,'Time Entries'!M2:M200,'Time Entries'!N2:N200,'Time Entries'!O2:O200,'Time Entries'!P2:P200,'Time Entries'!S2:S200,'Time Entries'!T2:T200},'Time Entries'!B2:B200=$B$3,'Time Entries'!F2:F200>=VLOOKUP($B$4,'Pay Periods'!$A:$O,4,FALSE),'Time Entries'!F2:F200<=VLOOKUP($B$4,'Pay Periods'!$A:$O,5,FALSE)))
A30: Total Hours | B30: =IF($B$10<>"OK - worker/pay period match",0,SUMIFS('Time Entries'!$J:$J,'Time Entries'!$B:$B,$B$3,'Time Entries'!$F:$F,">="&VLOOKUP($B$4,'Pay Periods'!$A:$O,4,FALSE),'Time Entries'!$F:$F,"<="&VLOOKUP($B$4,'Pay Periods'!$A:$O,5,FALSE),'Time Entries'!$P:$P,"<>Draft",'Time Entries'!$P:$P,"<>Rejected"))
A31: Gross Pay | B31: =IF($B$10<>"OK - worker/pay period match",0,SUMIFS('Time Entries'!$L:$L,'Time Entries'!$B:$B,$B$3,'Time Entries'!$F:$F,">="&VLOOKUP($B$4,'Pay Periods'!$A:$O,4,FALSE),'Time Entries'!$F:$F,"<="&VLOOKUP($B$4,'Pay Periods'!$A:$O,5,FALSE),'Time Entries'!$P:$P,"<>Draft",'Time Entries'!$P:$P,"<>Rejected"))
A32: Reimbursements | B32: =IF($B$10<>"OK - worker/pay period match",0,SUMIFS('Time Entries'!$M:$M,'Time Entries'!$B:$B,$B$3,'Time Entries'!$F:$F,">="&VLOOKUP($B$4,'Pay Periods'!$A:$O,4,FALSE),'Time Entries'!$F:$F,"<="&VLOOKUP($B$4,'Pay Periods'!$A:$O,5,FALSE),'Time Entries'!$P:$P,"<>Draft",'Time Entries'!$P:$P,"<>Rejected"))
A33: Deductions | B33: =IF($B$10<>"OK - worker/pay period match",0,SUMIFS('Time Entries'!$N:$N,'Time Entries'!$B:$B,$B$3,'Time Entries'!$F:$F,">="&VLOOKUP($B$4,'Pay Periods'!$A:$O,4,FALSE),'Time Entries'!$F:$F,"<="&VLOOKUP($B$4,'Pay Periods'!$A:$O,5,FALSE),'Time Entries'!$P:$P,"<>Draft",'Time Entries'!$P:$P,"<>Rejected"))
A34: Net Pay | B34: =B31+B32-B33

Sheet Access Status Demo
A1: Access Status Demo
A2: Visual guide to future-use access versus historical proof access.
A4: Active worker | D4: Inactive worker | G4: Former / read-only
A5: Can submit new time Can appear on Schedule Can receive admin notices | D5: Cannot receive new time entries Historical rows stay visible Proof can still be regenerated | G5: No future-use workflow Proof archive remains available Admin should not delete records
A10: Rule | B10: Active | C10: Inactive | D10: Former / Read-only | E10: Admin Note
A11: Create new time entry | B11: Yes | C11: No | D11: No | E11: Inactive means future-use access is stopped.
A12: View historical proof | B12: Yes | C12: Yes | D12: Yes | E12: Proof protection survives status changes.
A13: Appear in current schedule | B13: Yes | C13: No | D13: No | E13: Schedule is planning, not proof.
A14: Keep correction history | B14: Yes | C14: Yes | D14: Yes | E14: Corrections stay visible, not silent.
A17: Demo takeaway
A18: Admin can stop future access, but should not delete historical rows. Worker proof remains tied to workbook records.

Sheet Workflow Demo
A1: Workflow Demo
A2: One-screen view of the CrewPay Ledger operating flow.
A4: 1. Worker enters time | D4: 2. Worker submits | G4: 3. Admin reviews | J4: 4. Approve / Reject
A5: Draft row in Time Entries | C5: -> | D5: Status becomes Submitted | F5: -> | G5: Approve, reject, or request correction | I5: -> | J5: Decision remains visible
J9: ->
A10: 5. Pay period created | D10: 6. Worker Proof available | G10: 7. Proof exported | J10: 8. Read-only archive
A11: Totals summarize approved time | C11: -> | D11: Selected worker/pay period only | F11: -> | G11: PDF/CSV export logged | I11: -> | J11: Inactive workers keep proof history
A16: Source-of-truth rule
A17: Schedule, Admin Notices, Calendar sync, and export files are helper/reference layers. Time Entries, Pay Periods, Correction Log, and Worker Proof remain the proof trail.

Sheet Proof Exports
A1: Export ID | B1: Worker ID | C1: Worker Name | D1: Pay Period ID | E1: Export Type | F1: Generated At | G1: Generated By | H1: Export Reference | I1: Notes
A2: X-5001 | B2: W-1001 | C2: Maya Ellis | D2: P-4001 | E2: Print | F2: 46181.503 | G2: Admin Demo | H2: Printed proof packet | I2: Worker-specific proof generated from workbook records.
A3: X-5002 | B3: W-1003 | C3: Priya Shah | D3: P-4003 | E3: CSV | F3: 46182.396 | G3: Admin Demo | H3: CSV proof export | I3: Inactive worker proof regenerated after access status changed.

Sheet Access Log
A1: Log ID | B1: Worker ID | C1: Worker Name | D1: Previous Status | E1: New Status | F1: Changed At | G1: Changed By | H1: Reason
A2: A-6001 | B2: W-1003 | C2: Priya Shah | D2: Active | E2: Inactive | F2: 46182.333 | G2: Admin Demo | H2: End of assignment; historical proof retained.

Sheet Correction Log
A1: Correction ID | B1: Entry ID | C1: Worker ID | D1: Worker Name | E1: Pay Period ID | F1: Correction Date | G1: Corrected By | H1: Correction Reason | I1: Original Value Summary | J1: New Value Summary | K1: Notes | M1: Correction rule
A2: C-7001 | B2: T-3005 | C2: W-1003 | D2: Priya Shah | E2: P-4003 | F2: 46181 | G2: Admin Demo | H2: Add missing reimbursement | I2: Reimbursement 0 | J2: Reimbursement 15 | K2: Correction visible in Time Entries and log. | M2: Corrections are visible records. Do not silently overwrite proof.

Sheet Schedule
A1: Schedule ID | B1: Job ID | C1: Job Name | D1: Worker ID | E1: Worker Name | F1: Scheduled Date | G1: Start Time | H1: End Time | I1: Schedule Status | J1: Calendar Event ID | K1: Notes | M1: Schedule boundary
A2: S-8001 | B2: J-2001 | C2: Oak Ridge Units | D2: W-1001 | E2: Maya Ellis | F2: 46184 | G2: 0.33333333 | H2: 0.66666667 | I2: Scheduled | J2: cal-demo-oak-001 | K2: Planning only; not proof. | M2: Planning and Calendar reference only. Not proof.
A3: S-8002 | B3: J-2002 | C3: Bluebird Cafe Refresh | D3: W-1002 | E3: Leo Grant | F3: 46185 | G3: 0.375 | H3: 0.54166667 | I3: Planned | K3: Schedule reference only.

Sheet Admin Notices
A1: Notice ID | B1: Created At | C1: Created By | D1: Recipient Type | E1: Worker ID | F1: Worker Name | G1: Subject | H1: Message | I1: Related Pay Period ID | J1: Delivery Method | K1: Notice Status | L1: Sent At | M1: Notes | O1: Notice boundary
A2: N-9001 | B2: 46181.51 | C2: Admin Demo | D2: Worker | E2: W-1001 | F2: Maya Ellis | G2: Proof ready | H2: Your paid proof packet is ready in the workbook. | I2: P-4001 | J2: Workbook | K2: Posted | L2: 46181.51 | M2: One-way notice, not chat or proof. | O2: One-way admin notices only. Not chat and not proof.
A3: N-9002 | B3: 46182.347 | C3: Admin Demo | D3: All Active Workers | G3: Schedule reminder | H3: Check the Schedule tab for upcoming planned work. | J3: Email Ready | K3: Draft | M3: Email-ready text only; no send automation.

Sheet Calendar Sync Log
A1: Calendar Log ID | B1: Job ID | C1: Job Name | D1: Worker ID | E1: Worker Name | F1: Calendar Event ID | G1: Event Date | H1: Sync Status | I1: Last Synced At | J1: Notes | L1: Calendar boundary
A2: G-10001 | B2: J-2001 | C2: Oak Ridge Units | D2: W-1001 | E2: Maya Ellis | F2: cal-demo-oak-001 | G2: 46184 | H2: Not Synced | J2: Calendar is reference only, not proof. | L2: Calendar mirrors schedule references. It never creates proof.

Sheet Dropdown Lists
A1: Access Status | B1: Job Status | C1: Approval Status | D1: Pay Period Status | E1: Payment Status | F1: Export Type | G1: Schedule Status | H1: Recipient Type | I1: Delivery Method | J1: Notice Status | K1: Sync Status | M1: Demo Config
A2: Active | B2: Active | C2: Draft | D2: Open | E2: Unpaid | F2: Print | G2: Planned | H2: Worker | I2: Workbook | J2: Draft | K2: Not Synced | M2: Support/config tab for demo dropdowns. Not part of the public workflow.
A3: Inactive | B3: Paused | C3: Submitted | D3: Finalized | E3: Paid | F3: PDF | G3: Scheduled | H3: All Active Workers | I3: Email Ready | J3: Posted | K3: Synced
B4: Closed | C4: Approved | D4: Paid | F4: CSV | G4: Completed | I4: Gmail Sent | J4: Sent | K4: Failed
C5: Finalized | G5: Canceled | J5: Archived | K5: Skipped
C6: Paid
C7: Rejected
